HongshanHuiChuangyeZhishiShouceV20BanFix1/README.md
HongshanHuiChuangyeZhishiShouceV20BanFix1/__init__.py
HongshanHuiChuangyeZhishiShouceV20BanFix1/__main__.py
HongshanHuiChuangyeZhishiShouceV20BanFix1/file.epub
HongshanHuiChuangyeZhishiShouceV20BanFix1/index.html
HongshanHuiChuangyeZhishiShouceV20BanFix1/css/__init__.py
HongshanHuiChuangyeZhishiShouceV20BanFix1/css/annotations.css
HongshanHuiChuangyeZhishiShouceV20BanFix1/css/main.css
HongshanHuiChuangyeZhishiShouceV20BanFix1/css/normalize.css
HongshanHuiChuangyeZhishiShouceV20BanFix1/css/popup.css
HongshanHuiChuangyeZhishiShouceV20BanFix1/font/__init__.py
HongshanHuiChuangyeZhishiShouceV20BanFix1/font/fontello.eot
HongshanHuiChuangyeZhishiShouceV20BanFix1/font/fontello.svg
HongshanHuiChuangyeZhishiShouceV20BanFix1/font/fontello.ttf
HongshanHuiChuangyeZhishiShouceV20BanFix1/font/fontello.woff
HongshanHuiChuangyeZhishiShouceV20BanFix1/img/__init__.py
HongshanHuiChuangyeZhishiShouceV20BanFix1/img/annotator-glyph-sprite.png
HongshanHuiChuangyeZhishiShouceV20BanFix1/img/annotator-icon-sprite.png
HongshanHuiChuangyeZhishiShouceV20BanFix1/img/apple-touch-icon.png
HongshanHuiChuangyeZhishiShouceV20BanFix1/img/cancelfullscreen.png
HongshanHuiChuangyeZhishiShouceV20BanFix1/img/close.png
HongshanHuiChuangyeZhishiShouceV20BanFix1/img/fullscreen.png
HongshanHuiChuangyeZhishiShouceV20BanFix1/img/loader.gif
HongshanHuiChuangyeZhishiShouceV20BanFix1/img/menu-icon.png
HongshanHuiChuangyeZhishiShouceV20BanFix1/img/save.png
HongshanHuiChuangyeZhishiShouceV20BanFix1/img/saved.png
HongshanHuiChuangyeZhishiShouceV20BanFix1/img/settings-s.png
HongshanHuiChuangyeZhishiShouceV20BanFix1/img/settings.png
HongshanHuiChuangyeZhishiShouceV20BanFix1/img/star.png
HongshanHuiChuangyeZhishiShouceV20BanFix1/js/__init__.py
HongshanHuiChuangyeZhishiShouceV20BanFix1/js/epub.js
HongshanHuiChuangyeZhishiShouceV20BanFix1/js/epub.min.js
HongshanHuiChuangyeZhishiShouceV20BanFix1/js/epub.min.map
HongshanHuiChuangyeZhishiShouceV20BanFix1/js/hooks.min.js
hongshan_hui_chuangye_zhishi_shouce_v2_0_ban_fix1-2025.3.25.1.dist-info/METADATA
hongshan_hui_chuangye_zhishi_shouce_v2_0_ban_fix1-2025.3.25.1.dist-info/WHEEL
hongshan_hui_chuangye_zhishi_shouce_v2_0_ban_fix1-2025.3.25.1.dist-info/entry_points.txt
hongshan_hui_chuangye_zhishi_shouce_v2_0_ban_fix1-2025.3.25.1.dist-info/top_level.txt
hongshan_hui_chuangye_zhishi_shouce_v2_0_ban_fix1-2025.3.25.1.dist-info/RECORD
